framecat/__init__.py
framecat/cli.py
framecat/cli_interface.py
framecat/rendering.py
framecat-0.1.10.dist-info/LICENSE
framecat-0.1.10.dist-info/METADATA
framecat-0.1.10.dist-info/WHEEL
framecat-0.1.10.dist-info/entry_points.txt
framecat-0.1.10.dist-info/top_level.txt
framecat-0.1.10.dist-info/RECORD
