Metadata-Version: 2.1
Name: framecat
Version: 0.1.10
Author-email: Simon le Cleac'h <simonlch.edu@gmail.com>
License: MIT License
Classifier: Programming Language :: Python :: 3
Classifier: License :: OSI Approved :: MIT License
Classifier: Operating System :: OS Independent
Requires-Python: >=3.9
License-File: LICENSE
Requires-Dist: colorlog>=6.8.2
Requires-Dist: pytest>=7.4.2
Requires-Dist: pytest-cov>=4.1.0
Requires-Dist: pillow>=9.0.0
